unbounceapi/__init__.py
unbounceapi/accounts.py
unbounceapi/client.py
unbounceapi/domains.py
unbounceapi/leads.py
unbounceapi/page_groups.py
unbounceapi/pages.py
unbounceapi/sub_accounts.py
unbounceapi/users.py
unbounce_python_api-1.3.5.dist-info/LICENSE.txt
unbounce_python_api-1.3.5.dist-info/METADATA
unbounce_python_api-1.3.5.dist-info/WHEEL
unbounce_python_api-1.3.5.dist-info/top_level.txt
unbounce_python_api-1.3.5.dist-info/RECORD
