Metadata-Version: 2.1
Name: unbounce-python-api
Version: 1.3.5
Summary: An Unbounce API wrapper written in python.
Home-page: https://github.com/yoshiohasegawa/unbounce-python-api
Download-URL: https://github.com/yoshiohasegawa/unbounce-python-api/archive/refs/tags/v1.3.5.tar.gz
Author: Yoshio Hasegawa
Author-email: yoshio.seisuke.hasegawa@gmail.com
License: MIT
Keywords: Unbounce,API,Wrapper
Classifier: Development Status :: 4 - Beta
Classifier: Intended Audience :: Developers
Classifier: Topic :: Software Development :: Build Tools
Classifier: License :: OSI Approved :: MIT License
Classifier: Programming Language :: Python :: 3.6
Classifier: Programming Language :: Python :: 3.7
License-File: LICENSE.txt
Requires-Dist: requests
Requires-Dist: pytest
